{
  "lecturas": [
    {
      "tipo": "perfil_gestor",
      "titulo": "Citywire — Rafael Ortega Salvador",
      "url": "https://citywire.com/selector/manager/profile/rafael-ortega-salvador",
      "fuente": "citywire.com",
      "fecha": "",
      "descripcion": "Perfil de Rafael Ortega Salvador en Citywire Selector"
    },
    {
      "tipo": "perfil_gestor",
      "titulo": "Citywire — Carlos Santiso Pombo",
      "url": "https://citywire.com/selector/manager/profile/carlos-santiso-pombo",
      "fuente": "citywire.com",
      "fecha": "",
      "descripcion": "Perfil de Carlos Santiso Pombo en Citywire Selector"
    }
  ],
  "generado": "2026-04-05T09:50:29.400176"
}