{
  "isin": "IE00B6T42S66",
  "fund_name": "Trojan Fund (Ireland)",
  "timestamp": "2026-04-20T09:30:16.186963",
  "stats": {
    "total": 4,
    "skipped_already_done": 0,
    "skipped_no_text": 0,
    "extracted_ok": 4,
    "extracted_error": 0
  },
  "cartas": [
    {
      "periodo": "",
      "deep_ok": true,
      "error": null
    },
    {
      "periodo": "",
      "deep_ok": true,
      "error": null
    },
    {
      "periodo": "",
      "deep_ok": true,
      "error": null
    },
    {
      "periodo": "",
      "deep_ok": true,
      "error": null
    }
  ]
}