{
  "isin": "ES0182527038",
  "fund_name": "CARTESIO Y, FI",
  "gestora": "CARTESIO INVERSIONES, SGIIC, S.A.",
  "generated": "2026-04-23T20:15:53.682972",
  "num_readings": 5,
  "analisis_completos": [
    {
      "url": "https://markets.ft.com/data/funds/tearsheet/summary?s=es0182527038:eur",
      "source": "Financial Times",
      "source_type": "analisis",
      "quality": "high",
      "titulo": "Cartesio Y FI",
      "autor": null,
      "fecha": "2026-04-22",
      "tipo": "resena",
      "resumen": "El fondo Cartesio Y FI (ES0182527038) es una sociedad de inversión de capital variable domiciliada en España, lanzada en febrero de 2004. Se clasifica en la categoría de asignación flexible en euros de Morningstar y sigue un estilo de inversión de valor en grandes capitalizaciones. A fecha de abril de 2026, ha registrado una rentabilidad del +22.22% en el último año. Gestiona un patrimonio de 268.13 millones de GBP y su comisión de gestión continua es del 0.87%.",
      "puntos_clave": [
        "ISIN: ES0182527038",
        "Rentabilidad a 1 año: +22.22% (a 22 de abril de 2026)",
        "Patrimonio bajo gestión (AUM): 268.13m GBP (a 31 de marzo de 2026)",
        "Comisión de gestión continua (Ongoing charge): 0.87%",
        "Estilo de inversión: Valor, Grandes Capitalizaciones",
        "Categoría Morningstar: EUR Flexible Allocation",
        "Domicilio: España",
        "Fecha de lanzamiento: 23 de febrero de 2004",
        "Gestores mencionados: Juan Antonio Bertrán, Cayetano Cornet, Álvaro Martínez, Ignacio Sanz, Ignacio Carvajal, Jorge Losa",
        "Principales activos: Banca Monte dei Paschi di Siena SpA, Spain (Kingdom of) 0%, MERLIN Properties SOCIMI SA, TotalEnergies SE, AXA SA",
        "Asignación por tipo de activo: Acciones no británicas (73.66%), Efectivo (11.40%), Acciones británicas (10.29%), Bonos no británicos (4.65%)",
        "Asignación por región: Eurozona (59.39%), Reino Unido (10.29%), Europa - ex Euro (6.62%)"
      ],
      "opinion_sobre_fondo": null,
      "datos_mencionados": {
        "aum": "268.13m GBP",
        "rentabilidad": "+22.22% (1 año)",
        "rating": null,
        "comisiones": "0.87% (Ongoing charge)",
        "gestores": [
          "Juan Antonio Bertrán",
          "Cayetano Cornet",
          "Álvaro Martínez",
          "Ignacio Sanz",
          "Ignacio Carvajal",
          "Jorge Losa"
        ]
      },
      "citas_relevantes": [
        "1 Year change +22.22%",
        "Fund size 268.13m GBP",
        "Ongoing charge 0.87%",
        "Morningstar category EUR Flexible Allocation",
        "Investment Style: Value",
        "Market Cap: Large",
        "Domicile: Spain",
        "Launch date 23 Feb 2004"
      ]
    },
    {
      "url": "https://markets.ft.com/data/funds/tearsheet/holdings?s=ES0182527038:EUR",
      "source": "Financial Times",
      "source_type": "analisis",
      "quality": "high",
      "titulo": "Cartesio Y FI - Financial Times Fund Page",
      "autor": null,
      "fecha": "2026-04-22",
      "tipo": "fund_update",
      "resumen": "El fondo Cartesio Y FI (ES0182527038) ha registrado una rentabilidad del +22.22% en el último año, con datos actualizados a abril de 2026. Su cartera, a diciembre de 2025, muestra una fuerte inclinación hacia acciones no británicas (73.66%) y una concentración geográfica en Europa, especialmente en la Eurozona (59.39%). Los sectores de Servicios Financieros e Industriales son los más representados, y las diez principales posiciones constituyen el 34.25% del patrimonio. La información es proporcionada por Financial Times y Morningstar, advirtiendo que el rendimiento pasado no es indicativo de resultados futuros.",
      "puntos_clave": [
        "El fondo Cartesio Y FI (ES0182527038) tuvo una rentabilidad del +22.22% en el último año.",
        "La asignación de activos a diciembre de 2025 incluye un 73.66% en acciones no británicas y un 11.40% en efectivo.",
        "Geográficamente, el 76.30% de la cartera está en la Gran Europa, con un 59.39% en la Eurozona.",
        "Los sectores más ponderados son Servicios Financieros (15.26%) e Industriales (11.76%).",
        "Las diez principales posiciones representan el 34.25% del portfolio.",
        "Los datos son de Financial Times y Morningstar, con fecha de actualización de precios a 22 de abril de 2026 y de cartera a 31 de diciembre de 2025."
      ],
      "opinion_sobre_fondo": null,
      "datos_mencionados": {
        "aum": null,
        "rentabilidad": "+22.22% (1 Year change)",
        "rating": null,
        "comisiones": null,
        "gestores": []
      },
      "citas_relevantes": [
        "1 Year change +22.22%",
        "Data delayed at least 15 minutes, as of Apr 22 2026.",
        "Non-UK stock 73.66%",
        "Cash 11.40%",
        "Greater Europe 76.30%",
        "Eurozone 59.39%",
        "Financial Services 15.26%",
        "Per cent of portfolio in top 10 holdings: 34.25%",
        "Past performance is not necessarily a guide to future performance; unit prices may fall as well as rise.",
        "All data shown on this page, unless noted otherwise is Data Source and Copyright: Morningstar, Inc. 2026"
      ]
    },
    {
      "url": "https://markets.ft.com/data/funds/tearsheet/risk?s=ES0182527038:EUR",
      "source": "Financial Times",
      "source_type": "analisis",
      "quality": "high",
      "titulo": "Ficha de Fondo Cartesio Y FI",
      "autor": null,
      "fecha": "2026-04-22",
      "tipo": "fund_update",
      "resumen": "El Financial Times presenta una ficha de datos para el fondo Cartesio Y FI (ES0182527038), mostrando su precio actual de 3.829,77 EUR y una rentabilidad del +22,22% a un año. Los datos, actualizados al 22 de abril de 2026, provienen de Morningstar. El artículo incluye advertencias estándar sobre la naturaleza no-asesora de la información y que el rendimiento pasado no garantiza resultados futuros.",
      "puntos_clave": [
        "Identificación del fondo: Cartesio Y FI (ES0182527038).",
        "Precio actual de la participación: 3.829,77 EUR.",
        "Cambio diario de la participación: -0,09%.",
        "Rentabilidad a 1 año: +22,22%.",
        "Fecha de actualización de los datos: 22 de abril de 2026.",
        "Fuente de los datos: Morningstar.",
        "Advertencia de que el rendimiento pasado no es garantía de resultados futuros.",
        "El contenido no constituye asesoramiento de inversión."
      ],
      "opinion_sobre_fondo": null,
      "datos_mencionados": {
        "aum": null,
        "rentabilidad": "Cambio diario: -0.09%; Rentabilidad a 1 año: +22.22%",
        "rating": null,
        "comisiones": null,
        "gestores": []
      },
      "citas_relevantes": [
        "Price (EUR) 3,829.77",
        "Today's Change -3.26 / -0.09%",
        "1 Year change +22.22%",
        "Data delayed at least 15 minutes, as of Apr 22 2026.",
        "Past performance is not necessarily a guide to future performance; unit prices may fall as well as rise.",
        "All data shown on this page, unless noted otherwise is Data Source and Copyright: Morningstar, Inc. 2026",
        "Neither Morningstar nor its content providers are responsible for any damages or losses arising from any use of this information. Past performance is no guarantee of future results."
      ]
    }
  ],
  "otros_readings": [
    {
      "url": "https://www.finect.com/fondos-inversion/ES0182527038-Cartesio_y_fi",
      "source": "Finect",
      "source_type": "articulo",
      "quality": "medium",
      "titulo": "Cartesio Y FI",
      "autor": null,
      "fecha": "2026-04-21",
      "tipo": "resena",
      "resumen": "El fondo Cartesio Y FI (ES0182527038), gestionado por Cartesio Inversiones SGIIC, es un fondo de la categoría Mixtos Flexibles EUR. Cuenta con un patrimonio de 306,9 millones de euros y ha registrado una rentabilidad del +10,15% a 5 años. Su nivel de riesgo es de 3 sobre 7, y sus gastos corrientes ascienden al 1,020%.",
      "puntos_clave": [
        "El fondo es Cartesio Y FI, con ISIN ES0182527038.",
        "La gestora es Cartesio Inversiones SGIIC.",
        "Pertenece a la categoría Mixtos Flexibles EUR.",
        "Su patrimonio asciende a 306,9 millones de euros.",
        "Ha obtenido una rentabilidad del +10,15% a 5 años.",
        "El nivel de riesgo del fondo es 3 sobre 7.",
        "Las comisiones incluyen un 0,900% de gestión, 5,000% de éxito y 0,055% de custodia, con gastos corrientes del 1,020%.",
        "La fecha de inicio del fondo es el 23 de febrero de 2004.",
        "Su benchmark es MSCI Europe Net TR in EUR."
      ],
      "opinion_sobre_fondo": null,
      "datos_mencionados": {
        "aum": "306,9 M€",
        "rentabilidad": "+10,15% (5 años)",
        "rating": null,
        "comisiones": "Comisión de gestión: 0,900%; Comisión de éxito: 5,000%; Comisión de custodia: 0,055%; Gastos corrientes: 1,020%; Comisión de reembolso: 0,000%; Comisión de suscripción: 0,000%",
        "gestores": []
      },
      "citas_relevantes": [
        "Cartesio Y FI",
        "ES0182527038",
        "Gestora: Cartesio Inversiones SGIIC",
        "Categoría: Mixtos Flexibles EUR",
        "Benchmark MSCI Europe Net TR in EUR",
        "Patrimonio del fondo 306,9 M€",
        "Fecha de inicio 23/02/2004",
        "Comisión de gestión 0,900 %",
        "Comisión de éxito 5,000 %",
        "Comisión de custodia 0,055 %",
        "Gastos corrientes 1,020 %",
        "Comisión de reembolso 0,000 %",
        "Comisión de suscripción 0,000 %",
        "5 años + 10,15 %",
        "Riesgo 3 / 7",
        "Gastos 1,020 %",
        "Última actualización 21 de abril de 2026"
      ]
    },
    {
      "url": "https://www.finect.com/fondos-inversion/gestoras/76e1934f-Cartesio_inversiones_sgiic",
      "source": "Finect",
      "source_type": "articulo",
      "quality": "medium",
      "titulo": null,
      "autor": null,
      "fecha": null,
      "tipo": "resena",
      "resumen": "El texto presenta información clave sobre el fondo Cartesio Y FI (ES0182527038), gestionado por Cartesio Inversiones SGIIC. Este fondo, clasificado en la categoría de Mixtos Flexibles EUR, ha registrado una rentabilidad del +5,23% en el año y del +10,15% a cinco años. Su nivel de riesgo se sitúa en 3 sobre 7, y sus gastos ascienden al 1,020%.",
      "puntos_clave": [
        "El fondo Cartesio Y FI (ES0182527038) es gestionado por Cartesio Inversiones SGIIC.",
        "Pertenece a la categoría de Mixtos Flexibles EUR.",
        "Ha obtenido una rentabilidad del +5,23% en el año.",
        "Su rentabilidad a 5 años es del +10,15%.",
        "Presenta un nivel de riesgo de 3 sobre 7.",
        "Los gastos asociados al fondo son del 1,020%."
      ],
      "opinion_sobre_fondo": null,
      "datos_mencionados": {
        "aum": null,
        "rentabilidad": "en el año + 5,23 %, 5 años + 10,15 %",
        "rating": null,
        "comisiones": "1,020 %",
        "gestores": []
      },
      "citas_relevantes": [
        "Cartesio Y FI",
        "ES0182527038",
        "Clase única",
        "en el año + 5,23 %",
        "5 años + 10,15 %",
        "Riesgo 3 / 7",
        "Gastos 1,020 %",
        "Gestora : Cartesio Inversiones SGIIC",
        "Categoría : Mixtos Flexibles EUR"
      ]
    }
  ],
  "fuentes_consultadas": [
    "https://markets.ft.com/data/funds/tearsheet/summary?s=es0182527038:eur",
    "https://markets.ft.com/data/funds/tearsheet/holdings?s=ES0182527038:EUR",
    "https://markets.ft.com/data/funds/tearsheet/risk?s=ES0182527038:EUR",
    "https://www.barrons.com/market-data/stocks/xd4?countrycode=de&iso=xmun",
    "https://www.barrons.com/market-data/stocks/xd4?countrycode=de&iso=xfra",
    "https://www.finect.com/fondos-inversion/ES0182527038-Cartesio_y_fi",
    "https://www.finect.com/fondos-inversion/gestoras/76e1934f-Cartesio_inversiones_sgiic"
  ]
}