{
  "isin": "ES0128520006",
  "fund_name": "RENTA 4 MONETARIO, FI",
  "gestora": "RENTA 4 GESTORA, S.G.I.I.C., S.A.",
  "generated": "2026-04-23T20:34:58.712231",
  "num_readings": 12,
  "analisis_completos": [
    {
      "url": "https://markets.ft.com/data/equities/tearsheet/profile?s=R4:MCE",
      "source": "Financial Times",
      "source_type": "analisis",
      "quality": "high",
      "titulo": "Renta 4 Banco SA - Financial Times",
      "autor": null,
      "fecha": "2026-04-23",
      "tipo": null,
      "resumen": "Este texto del Financial Times proporciona un perfil detallado de Renta 4 Banco SA, una institución financiera española. Describe sus principales áreas de actividad, incluyendo servicios de corretaje, gestión de activos y servicios corporativos. También presenta datos financieros clave de la empresa, como ingresos y beneficios, así como información sobre el rendimiento de sus acciones y sus principales accionistas institucionales. Sin embargo, el texto no contiene información específica sobre el fondo RENTA 4 MONETARIO, FI.",
      "puntos_clave": [],
      "opinion_sobre_fondo": null,
      "datos_mencionados": {
        "aum": null,
        "rentabilidad": null,
        "rating": null,
        "comisiones": null,
        "gestores": []
      },
      "citas_relevantes": []
    },
    {
      "url": "https://markets.ft.com/data/equities/tearsheet/profile?s=REN:MCE",
      "source": "Financial Times",
      "source_type": "analisis",
      "quality": "high",
      "titulo": "Renta Corporacion Real Estate SA",
      "autor": null,
      "fecha": "2026-04-23",
      "tipo": null,
      "resumen": "El texto proporcionado por Financial Times detalla el perfil de la empresa Renta Corporacion Real Estate SA, incluyendo sus actividades en el sector inmobiliario, datos financieros y su historial de insolvencia. También lista a sus principales accionistas institucionales. Sin embargo, el texto no contiene información específica sobre el fondo RENTA 4 MONETARIO, FI (ES0128520006).",
      "puntos_clave": [],
      "opinion_sobre_fondo": null,
      "datos_mencionados": {
        "aum": null,
        "rentabilidad": null,
        "rating": null,
        "comisiones": null,
        "gestores": []
      },
      "citas_relevantes": []
    },
    {
      "url": "https://markets.ft.com/data/equities/tearsheet/profile?s=ALNT:MCE",
      "source": "Financial Times",
      "source_type": "analisis",
      "quality": "high",
      "titulo": null,
      "autor": null,
      "fecha": "2026-04-23",
      "tipo": null,
      "resumen": "El texto es un perfil de la empresa Alantra Partners SA, detallando sus operaciones y datos financieros. No se encuentra información específica sobre el fondo RENTA 4 MONETARIO, FI. Sin embargo, se menciona que Renta 4 Gestora SGIIC SA, la gestora asociada al fondo, es un accionista institucional de Alantra Partners SA, con una participación del 1.37%.",
      "puntos_clave": [
        "Renta 4 Gestora SGIIC SA, la gestora asociada al fondo, figura como accionista institucional de Alantra Partners SA.",
        "Renta 4 Gestora SGIIC SA posee el 1.37% de las acciones de Alantra Partners SA.",
        "La participación de Renta 4 Gestora SGIIC SA en Alantra Partners SA aumentó en un 47.54%."
      ],
      "opinion_sobre_fondo": null,
      "datos_mencionados": {
        "aum": null,
        "rentabilidad": null,
        "rating": null,
        "comisiones": null,
        "gestores": []
      },
      "citas_relevantes": [
        "Renta 4 Gestora SGIIC SA as of 31 Dec 2025 529.92k 1.37%",
        "Renta 4 Gestora SGIIC SA +170.76k / +47.54% 529.92k"
      ]
    },
    {
      "url": "https://markets.ft.com/data/funds/tearsheet/performance?s=ES0128520006:EUR",
      "source": "Financial Times",
      "source_type": "analisis",
      "quality": "high",
      "titulo": "Renta 4 Renta Fija 6 Meses FI",
      "autor": null,
      "fecha": "2026-04-22",
      "tipo": "fund_update",
      "resumen": "Este documento del Financial Times, con datos de Morningstar, presenta un perfil del fondo Renta 4 Renta Fija 6 Meses FI (ISIN ES0128520006). Muestra su precio actual, cambios diarios y anuales, y un desglose de la rentabilidad total a diferentes plazos. El fondo ha registrado una rentabilidad del +2.17% en un año y se compara favorablemente con la categoría EUR Money Market, situándose frecuentemente en el primer o segundo cuartil.",
      "puntos_clave": [
        "El fondo analizado es Renta 4 Renta Fija 6 Meses FI, con ISIN ES0128520006.",
        "Presenta una rentabilidad del +2.17% en el último año.",
        "Sus rentabilidades totales a 1, 3 y 5 años son +3.55%, +2.54% y +2.02% respectivamente.",
        "El fondo se posiciona consistentemente en el primer o segundo cuartil de su categoría (EUR Money Market) en la mayoría de los periodos.",
        "La información y los datos de rendimiento son proporcionados por Morningstar."
      ],
      "opinion_sobre_fondo": null,
      "datos_mencionados": {
        "aum": null,
        "rentabilidad": "1 Year change: +2.17%; Trailing total returns: 5 years: +2.02%, 3 years: +2.54%, 1 year: +3.55%, 6 months: +1.23%, 3 months: +0.28%, 1 month: +0.47%",
        "rating": "Fund quartile: 2nd (5 years), 2nd (3 years), 1st (1 year), 2nd (6 months), 2nd (3 months), 1st (1 month)",
        "comisiones": null,
        "gestores": []
      },
      "citas_relevantes": [
        "ES0128520006:EUR",
        "Price (EUR) 12.65",
        "Today's Change 0.001 / 0.01%",
        "1 Year change +2.17%",
        "Data delayed at least 15 minutes, as of Apr 22 2026.",
        "Renta 4 Renta Fija 6 Meses FI +3.55% (1 year)",
        "Fund quartile 1st (1 year)",
        "All data shown on this page, unless noted otherwise is Data Source and Copyright: Morningstar, Inc. 2026"
      ]
    },
    {
      "url": "https://markets.ft.com/data/funds/tearsheet/ratings?s=ES0128520006:EUR",
      "source": "Financial Times",
      "source_type": "analisis",
      "quality": "high",
      "titulo": "Renta 4 Renta Fija 6 Meses FI",
      "autor": null,
      "fecha": "2026-04-22",
      "tipo": "fund_update",
      "resumen": "Esta página del Financial Times presenta información clave sobre el fondo Renta 4 Renta Fija 6 Meses FI (ISIN ES0128520006). Muestra un precio actual de 12.65 EUR y una rentabilidad del +2.17% en el último año. El fondo está clasificado en la categoría EUR Money Market por Morningstar, que es la fuente principal de los datos.",
      "puntos_clave": [
        "El fondo es Renta 4 Renta Fija 6 Meses FI (ISIN ES0128520006).",
        "Su precio actual es de 12.65 EUR.",
        "Ha registrado una rentabilidad del +2.17% en el último año.",
        "Está clasificado en la categoría 'EUR Money Market' por Morningstar.",
        "Morningstar es la fuente principal de los datos mostrados."
      ],
      "opinion_sobre_fondo": "Neutral, ya que el texto es una ficha de datos y no contiene ninguna valoración editorial o de autor sobre el rendimiento o las perspectivas del fondo.",
      "datos_mencionados": {
        "aum": null,
        "rentabilidad": "+2.17% (1 año)",
        "rating": "Menciona una calificación general y lo clasifica en la categoría EUR Money Market.",
        "comisiones": null,
        "gestores": []
      },
      "citas_relevantes": [
        "ES0128520006:EUR",
        "Price (EUR) 12.65",
        "1 Year change +2.17%",
        "Data delayed at least 15 minutes, as of Apr 22 2026.",
        "Overall rating As of March 2026",
        "Category EUR Money Market",
        "All data shown on this page, unless noted otherwise is Data Source and Copyright: Morningstar, Inc. 2026"
      ]
    }
  ],
  "otros_readings": [
    {
      "url": "https://www.rankia.com/foros/fondos-inversion/temas/2072470-renta-4-monetario-fi",
      "source": "Rankia",
      "source_type": "comunidad",
      "quality": "medium",
      "titulo": null,
      "autor": null,
      "fecha": "2013-12-13",
      "tipo": "opinion",
      "resumen": "Un usuario busca opiniones sobre el fondo RENTA 4 MONETARIO, FI como alternativa a los depósitos a plazo fijo. Se pregunta sobre su seguridad, la influencia de las subidas de tipos de interés en su rentabilidad y sus comisiones. El fondo invierte principalmente en depósitos bancarios a corto plazo y deuda de alta calificación.",
      "puntos_clave": [
        "El fondo invierte en depósitos bancarios a menos de 1 año, deuda de alta calificación y un pequeño porcentaje en derivados.",
        "Las subidas en los tipos de interés pueden ser malas para su rentabilidad.",
        "Es considerado muy seguro."
      ],
      "opinion_sobre_fondo": null,
      "datos_mencionados": {
        "aum": null,
        "rentabilidad": "la rentabilidad no es pequeña",
        "rating": null,
        "comisiones": "menciona la existencia de comisiones",
        "gestores": []
      },
      "citas_relevantes": [
        "He estado mirando este fondo como alternativa a los depósitos a plazo fijo.",
        "Por lo que he podido leer es muy seguro aunque la rentabilidad no es pequeña.",
        "El fondo invierte en depósitos bancarios a menos de 1 año, deuda de alta calificación y un pequeño porcentaje en derivados.",
        "Leyendo la ficha del fondo indica que las subidas en los tipos de interés pueden ser malas para su rentabilidad.",
        "¿Que opinión os merece este fondo bajo el punto de vista de la seguridad?",
        "¿Y sus comisiones?"
      ]
    },
    {
      "url": "https://www.rankia.com/fondos-de-inversion/renta-4-fija-6-meses-fi-renta-4-gestora/foro?page=2",
      "source": "Rankia",
      "source_type": "comunidad",
      "quality": "medium",
      "titulo": "Foro de discusión sobre Renta 4 Monetario FI",
      "autor": null,
      "fecha": null,
      "tipo": "resena",
      "resumen": "El texto recopila discusiones de un foro de inversión centradas en el fondo Renta 4 Monetario FI (también identificado como Renta 4 Renta Fija 6 meses, FI). Los participantes debaten sobre la idoneidad del fondo como alternativa a las cuentas corrientes para gestionar el efectivo. Se plantean preguntas sobre su perfil de bajo riesgo y se buscan alternativas o comparaciones con otros productos similares. Las opiniones sobre su rendimiento y riesgo son variadas entre los usuarios.",
      "puntos_clave": [
        "Discusión sobre el fondo Renta 4 Monetario FI en un foro de inversión.",
        "Debate sobre si el fondo es una alternativa adecuada a las cuentas corrientes para el efectivo.",
        "Cuestionamientos y análisis sobre el bajo riesgo percibido del fondo.",
        "Búsqueda de alternativas y comparaciones con otros fondos monetarios o de renta fija a corto plazo."
      ],
      "opinion_sobre_fondo": "Mixta, ya que el texto recopila diversas opiniones de usuarios en un foro. Algunos lo ven como una buena opción para el efectivo y con buenos resultados, mientras que otros cuestionan su bajo riesgo y buscan alternativas. No hay una opinión unificada del autor del texto.",
      "datos_mencionados": {
        "aum": null,
        "rentabilidad": null,
        "rating": null,
        "comisiones": null,
        "gestores": []
      },
      "citas_relevantes": [
        "Supongo que ellos gracias al volumen que manejan puedan conseguir mejores...",
        "Exacto. Si tienes tu cash en el monetario en lugar de cc no te cobrarían nada",
        "Me quedaría los 2, ambos diferentes ambos están dando buenos resultados. Saludos",
        "¿Realmente tiene bajo riesgo el Renta4 Monetario?",
        "Conociendo la cartera, como muchos foreros detallan, cada uno ya sabe el riesgo que...",
        "Me estado mirando este hilo, dado que también busco una alternativa al monetario de R4;",
        "Por muy buena rentabilidad que tenga el PIMCO yo personalmente no lo puedo considerar..."
      ]
    },
    {
      "url": "https://www.rankia.com/foros/fondos-inversion/temas/2288202-hilo-fondos-ofrecidos-por-renta-4-opiniones-recomendaciones-experiencias",
      "source": "Rankia",
      "source_type": "comunidad",
      "quality": "medium",
      "titulo": "Inicio de hilo de discusión sobre fondos de Renta 4",
      "autor": null,
      "fecha": "2014-05-11",
      "tipo": "opinion",
      "resumen": "El texto es una publicación de foro que inicia un hilo de discusión sobre los fondos de Renta 4. El autor expresa una opinión positiva sobre Renta 4 como banco, destacando su buen servicio y asesoramiento a los clientes. Se presenta una lista de diversos fondos de Renta 4, clasificados por tipo, incluyendo el Renta 4 Monetario FI. El objetivo es que los usuarios compartan experiencias, opiniones e información sobre la gestión de estos fondos y sus perfiles.",
      "puntos_clave": [
        "Creación de un hilo de discusión para comentar sobre los fondos de Renta 4.",
        "Opinión positiva del autor sobre el servicio y asesoramiento de Renta 4 como entidad.",
        "Listado de fondos de Renta 4 por categorías, incluyendo el Renta 4 Monetario FI.",
        "Invitación a los usuarios a aportar información sobre la gestión de los fondos y sus perfiles de inversión."
      ],
      "opinion_sobre_fondo": null,
      "datos_mencionados": {
        "aum": null,
        "rentabilidad": null,
        "rating": null,
        "comisiones": null,
        "gestores": []
      },
      "citas_relevantes": [
        "Abro este hilo para ir comentando sobre la evolución, opinión, experiencias, formación de carteras, información de los propios fondos, etc... de los fondos que ofrece Renta 4",
        "Renta 4 es uno de los bancos, que por ahora, no suele engañar a sus clientes y desde mi experiencia ofrece un buen servicio y asesoramiento sobre los niveles de riesgo que puede cada uno asumir.",
        "Los fondos sobre los que me gustaria que se fuese hablando son los siguientes: [...] Renta 4 Monetario FI",
        "podamos ir comentado sobre estos fondos para que todos vayamos aprendiendo más e ir informándonos con aportaciones de información sobre la gestión de sus gestores, en qué invierten y en que momento pueden ser interesantes y para que perfiles."
      ]
    },
    {
      "url": "https://www.quefondos.com/es/fondos/analisis/refs/ref_02080-fondos-bajo-riesgo-ii.html",
      "source": "quefondos.com",
      "source_type": "articulo",
      "quality": "low",
      "titulo": "Fondos de bajo riesgo ( II )",
      "autor": "Sergio Ortega",
      "fecha": "2016-10-05",
      "tipo": "analisis_completo",
      "resumen": "El artículo, segunda parte de un análisis sobre fondos de bajo riesgo, examina productos de inversión de entidades financieras que ocupan del puesto 6 al 20 por patrimonio en España. Se centra en fondos con baja volatilidad (inferior al 2% anual), rentabilidades positivas a uno y tres años, denominados en euros y accesibles para inversores particulares con una inversión mínima inferior a 6.000 euros. Presenta una tabla con datos de rentabilidad y rating VDOS para varios fondos de estas gestoras, incluyendo el RENTA 4 MONETARIO, FI.",
      "puntos_clave": [
        "El artículo es la segunda parte de un análisis sobre fondos de inversión de bajo riesgo.",
        "Se enfoca en fondos de las entidades financieras que ocupan del puesto 6 al 20 por patrimonio en España.",
        "Los fondos seleccionados tienen baja volatilidad (<2% anual), rentabilidades positivas a 1 y 3 años, están denominados en euros y son para inversores particulares con inversión mínima <6.000 euros.",
        "El fondo RENTA 4 MONETARIO, FI se incluye en la lista, mostrando su categoría, rentabilidad anual y a 3 años, y rating VDOS."
      ],
      "opinion_sobre_fondo": "El artículo presenta el fondo RENTA 4 MONETARIO, FI como parte de un listado de fondos de bajo riesgo, proporcionando datos objetivos de rentabilidad y rating VDOS, pero no ofrece una opinión editorial o análisis cualitativo específico sobre el fondo. Por lo tanto, la opinión es neutral.",
      "datos_mencionados": {
        "aum": null,
        "rentabilidad": "0,30% (año), 2,91% (3 años)",
        "rating": "***** (VDOS)",
        "comisiones": null,
        "gestores": []
      },
      "citas_relevantes": [
        "RENTA 4 MONETARIO, FI",
        "MONETARIO EURO",
        "0,30%",
        "2,91%",
        "*****"
      ]
    },
    {
      "url": "https://www.quefondos.com/es/fondos/analisis/refs/ref571.html",
      "source": "quefondos.com",
      "source_type": "articulo",
      "quality": "low",
      "titulo": "Los fondos de inversión favoritos",
      "autor": "Sergio Ortega (VDOS)",
      "fecha": "2013-08-30",
      "tipo": "resena",
      "resumen": "El artículo de quefondos.com, publicado el 30/08/13, analiza los fondos de inversión más populares entre sus usuarios. Se destaca el interés en gestoras españolas como Renta 4 Gestora. El fondo RENTA 4 MONETARIO, FI, gestionado por Ignacio Vitoriano, figura entre los más consultados. Este fondo ha logrado rentabilidades superiores a la media de su categoría y se ha mantenido en el primer quintil durante los últimos cuatro años, lo que subraya su buen desempeño.",
      "puntos_clave": [
        "RENTA 4 MONETARIO, FI es uno de los fondos más consultados en la comunidad quefondos.com.",
        "El fondo es gestionado por Ignacio Vitoriano.",
        "Ha acumulado rentabilidades superiores a la media de su categoría.",
        "Se ha situado en el primer quintil de su categoría durante los últimos 4 años."
      ],
      "opinion_sobre_fondo": "Positiva, el fondo ha demostrado rentabilidades superiores a la media de su categoría y se ha mantenido en el primer quintil durante los últimos 4 años.",
      "datos_mencionados": {
        "aum": null,
        "rentabilidad": "superior a la media de su categoría, en el primer quintil durante los últimos 4 años",
        "rating": null,
        "comisiones": null,
        "gestores": [
          "Ignacio Vitoriano"
        ]
      },
      "citas_relevantes": [
        "Estos fondos son seguidos de cerca por los fondos RENTA 4 MONETARIO, FI gestionados por Ignacio Vitoriano",
        "Ambos fondos acumulan rentabilidades superiores a la media de sus respectivas categorías, lo que en el caso del Renta 4 Monetario le ha valido también para destacar en el primer quintil de su categoría, puesto que ocupa en los últimos 4 años."
      ]
    },
    {
      "url": "https://www.quefondos.com/es/fondos/analisis/refs/ref476.html",
      "source": "quefondos.com",
      "source_type": "articulo",
      "quality": "low",
      "titulo": "Comparando fondos: monetario euro - marzo 2013",
      "autor": "Sergio Ortega (VDOS)",
      "fecha": "2013-03-13",
      "tipo": "analisis_completo",
      "resumen": "El artículo de marzo de 2013 compara varios fondos monetarios euro, incluyendo RENTA 4 MONETARIO, FI, basándose en parámetros como el rating VDOS, rentabilidad y riesgo. Se seleccionaron fondos con un rating VDOS de 3 estrellas o superior y una aportación mínima inferior a 6.000 euros. Aunque DINERCAM, FI es destacado por su rentabilidad a corto plazo, RENTA 4 MONETARIO, FI es notable por su rentabilidad a largo plazo. El análisis también considera la relación rentabilidad/volatilidad y la inversión mínima.",
      "puntos_clave": [
        "El artículo compara varios fondos monetarios euro, incluyendo RENTA 4 MONETARIO, FI.",
        "RENTA 4 MONETARIO, FI fue seleccionado por tener un rating VDOS de 3 estrellas o superior y una aportación mínima inferior a 6.000 euros.",
        "RENTA 4 MONETARIO, FI es destacado por su rentabilidad a largo plazo.",
        "El análisis considera la rentabilidad a corto y largo plazo, la relación rentabilidad/volatilidad y la inversión mínima."
      ],
      "opinion_sobre_fondo": "Positiva, ya que el fondo RENTA 4 MONETARIO, FI es destacado por su rentabilidad a largo plazo.",
      "datos_mencionados": {
        "aum": null,
        "rentabilidad": "Menciona rentabilidad a largo plazo",
        "rating": "VDOS 3 Estrellas o superior",
        "comisiones": "Menciona la existencia de comisiones y la inversión mínima",
        "gestores": null
      },
      "citas_relevantes": [
        "RENTA 4 MONETARIO, FI",
        "se han seleccionado aquellos con un rating de 3 Estrellas VDOS o superior con una aportación mínima inferior a 6.000 Euros.",
        "Igualmente, es posible destacar el fondo RENTA 4 MONETARIO, FI por su rentabilidad a largo plazo.",
        "Para ello, calculamos el cociente (rentabilidad media/volatilidad), información que nos indicara que fondo tiene un mejor dato de rentabilidad en función del riesgo asumido en el último año, quedando ordenado del siguiente modo: EUROVALOR AHORRO CORTO PLAZO, FI, RENTA 4 MONETARIO, FI, INTERDIN TESORERIA, FI..."
      ]
    },
    {
      "url": "https://www.investing.com/funds/renta-4-monetario-fi-holdings",
      "source": "investing.com",
      "source_type": "articulo",
      "quality": "low",
      "titulo": "Renta 4 Monetario FI - Información General",
      "autor": null,
      "fecha": null,
      "tipo": "resena",
      "resumen": "El Renta 4 Monetario FI (ISIN: ES0128520006), gestionado por Renta 4 Gestora SGIIC S.A., es un fondo de renta fija con un patrimonio total de 1.460 millones de euros. Su cartera está mayoritariamente invertida en bonos (81.08%) y una parte en efectivo (18.92%), destacando una asignación significativa a bonos corporativos (82.939%). El fondo mantiene 176 posiciones largas y 1 corta, con Ibercaja Banco S.A. y BNP Paribas SA entre sus principales tenencias.",
      "puntos_clave": [
        "Fondo de renta fija gestionado por Renta 4 Gestora SGIIC S.A.",
        "ISIN: ES0128520006.",
        "Patrimonio total (AUM) de 1.460 millones de euros.",
        "La asignación de activos incluye 81.08% en bonos y 18.92% en efectivo.",
        "La asignación sectorial principal es en bonos corporativos (82.939%).",
        "El fondo tiene 176 posiciones largas y 1 posición corta."
      ],
      "opinion_sobre_fondo": null,
      "datos_mencionados": {
        "aum": "1.46B",
        "rentabilidad": null,
        "rating": null,
        "comisiones": null,
        "gestores": []
      },
      "citas_relevantes": [
        "ISIN: ES0128520006",
        "Issuer: Renta 4 Gestora SGIIC S.A.",
        "Asset Class: Bond",
        "Total Assets: 1.46B",
        "Cash 18.920",
        "Bonds 81.080",
        "Corporate 82.939",
        "Number of long holdings: 176",
        "Number of short holdings: 1"
      ]
    }
  ],
  "fuentes_consultadas": [
    "https://markets.ft.com/data/equities/tearsheet/profile?s=R4:MCE",
    "https://markets.ft.com/data/equities/tearsheet/profile?s=REN:MCE",
    "https://markets.ft.com/data/equities/tearsheet/profile?s=ALNT:MCE",
    "https://markets.ft.com/data/funds/tearsheet/performance?s=ES0128520006:EUR",
    "https://markets.ft.com/data/funds/tearsheet/ratings?s=ES0128520006:EUR",
    "https://www.rankia.com/foros/fondos-inversion/temas/2072470-renta-4-monetario-fi",
    "https://www.rankia.com/fondos-de-inversion/renta-4-fija-6-meses-fi-renta-4-gestora/foro?page=2",
    "https://www.rankia.com/foros/fondos-inversion/temas/2288202-hilo-fondos-ofrecidos-por-renta-4-opiniones-recomendaciones-experiencias",
    "https://www.quefondos.com/es/fondos/analisis/refs/ref_02080-fondos-bajo-riesgo-ii.html",
    "https://www.quefondos.com/es/fondos/analisis/refs/ref571.html",
    "https://www.quefondos.com/es/fondos/analisis/refs/ref476.html",
    "https://www.investing.com/funds/renta-4-monetario-fi-holdings"
  ]
}